{
  "metadata": {
    "id": "weekly_ai_1770833088940",
    "type": "weekly",
    "period": "2026-02-04 to 2026-02-11",
    "generatedAt": "2026-02-11T18:04:48.940Z",
    "userId": null,
    "aiStatus": {
      "keyUsed": "primary",
      "usingFallback": false,
      "primaryFailures": 0
    },
    "dataSnapshot": {
      "totalProducts": 19,
      "totalValue": 65777.55,
      "totalUnits": 1301,
      "ordersInPeriod": 7,
      "criticalAlerts": 5,
      "stockHealth": {
        "normal": 1,
        "lowStock": 6,
        "outOfStock": 0,
        "overstock": 12
      }
    },
    "analysis": {
      "stockDistribution": {
        "normal": 1,
        "lowStock": 6,
        "outOfStock": 0,
        "overstock": 12,
        "normalPercent": 5,
        "lowStockPercent": 32,
        "outOfStockPercent": 0,
        "overstockPercent": 63
      },
      "financialMetrics": {
        "turnoverRisk": "High",
        "capitalTiedUp": 80069.36000000002,
        "reorderInvestment": 199860.33000000002
      },
      "topPerformers": [
        {
          "id": 4,
          "name": "27\" 4K Monitor",
          "sku": "MONITOR-001",
          "description": "Professional 4K display",
          "supplier_id": 1,
          "unit_price": "499.99",
          "stock_quantity": 35,
          "reorder_level": 10,
          "created_at": "2026-02-04T17:24:02.047Z",
          "updated_at": "2026-02-04T17:24:02.047Z",
          "user_id": 8,
          "primary_state": "available",
          "last_movement_date": "2026-02-04T17:24:02.047Z",
          "supplier_name": "TechParts Inc",
          "total_value": "17499.65",
          "stock_status": "OVERSTOCK"
        },
        {
          "id": 20,
          "name": "saiodaod",
          "sku": "oniajsodi",
          "description": "ioasdioadio",
          "supplier_id": null,
          "unit_price": "123.00",
          "stock_quantity": 123,
          "reorder_level": 1230,
          "created_at": "2026-02-11T14:52:20.859Z",
          "updated_at": "2026-02-11T14:52:20.859Z",
          "user_id": 1,
          "primary_state": "available",
          "last_movement_date": "2026-02-11T14:52:20.859Z",
          "supplier_name": null,
          "total_value": "15129.00",
          "stock_status": "LOW_STOCK"
        },
        {
          "id": 7,
          "name": "Tablet 10\" Pro",
          "sku": "TABLET-001",
          "description": "Professional tablet with stylus",
          "supplier_id": 5,
          "unit_price": "649.99",
          "stock_quantity": 18,
          "reorder_level": 8,
          "created_at": "2026-02-04T17:24:02.047Z",
          "updated_at": "2026-02-04T17:24:02.047Z",
          "user_id": 8,
          "primary_state": "available",
          "last_movement_date": "2026-02-04T17:24:02.047Z",
          "supplier_name": "Hardware Express",
          "total_value": "11699.82",
          "stock_status": "NORMAL"
        }
      ],
      "criticalItems": 5
    },
    "optimizations": {
      "promptTokensUsed": 1811,
      "analysisDepth": 7,
      "cacheUsed": false,
      "generationTime": 11772
    }
  },
  "content": "**Weekly Inventory Report: 2026-02-04 to 2026-02-11**\n\n**To:** Management Team\n**From:** [Your Name/Inventory Analyst Department]\n**Date:** 2026-02-11\n**Subject:** Critical Inventory Review and Strategic Recommendations\n\n**Executive Summary**\n\nThis past week, our inventory stands at 1301 units across 19 products, valued at $65,777.55. While we have no products completely out of stock, our inventory health remains a significant concern. A staggering 63% of our products are overstocked, tying up substantial capital, while 32% are critically low, risking lost sales and customer dissatisfaction. Only one product (5%) is at optimal levels. This imbalance presents both immediate operational challenges and considerable financial implications, with over $80,000 in capital locked in excess stock and nearly $200,000 required for urgent reorders.\n\n**Key Issues Requiring Immediate Attention**\n\nThe most pressing concern is the **Business Laptop Pro**, which shows a negative stock balance of -42 units. This indicates either unfulfilled backorders or a significant data discrepancy that needs immediate investigation and resolution to prevent further customer impact.\n\nAdditionally, several high-value and fast-moving items are critically low:\n*   **saiodaod:** Only 123 units remaining, requiring a substantial reorder of 1107 units costing $136,161.00. This is our second highest-value product and a top priority.\n*   **Power Bank 20000mAh:** Only 3 units left, needing 12 more ($599.88).\n*   **Smart Watch:** Only 2 units left, needing 8 more ($1,999.92).\n\nWe also note \"aosijdaoisod\" is listed as critically low with 10 units, but shows \"need 0 more.\" This requires clarification to determine if it's an end-of-life product or a data error.\n\n**Stock Distribution and Business Impact**\n\nOur current stock distribution is far from ideal. The 63% overstock rate means a significant portion of our capital ($80,069.36) is tied up in slow-moving or excess inventory, increasing holding costs and obsolescence risk. For example, the **27\" 4K Monitor**, our highest-value product, is currently overstocked.\n\nConversely, the 32% of products running low, including high-value items like \"saiodaod,\" directly translates to missed sales opportunities and potential customer dissatisfaction. The fact that only 5% of our products are optimally stocked highlights a systemic issue in our forecasting and inventory management.\n\n**Financial Implications and Cash Flow**\n\nThe financial impact is substantial. We have **$80,069.36 tied up in excess inventory**, capital that could be better utilized elsewhere. Simultaneously, we face an urgent need for **$199,860.33 to cover critical reorders**. This creates a significant cash flow challenge, as we are over-invested in some areas while under-invested in others that are driving sales (e.g., USB-C Cable 2m was a top seller this period).\n\n**Actionable Recommendations**\n\n1.  **Immediate Action on Critical Lows:**\n    *   **Investigate Business Laptop Pro:** Urgently determine the cause of the negative stock and fulfill any outstanding orders.\n    *   **Prioritize Reorders:** Immediately initiate reorders for \"saiodaod,\"",
  "rawData": {
    "currentInventory": [
      {
        "id": 4,
        "name": "27\" 4K Monitor",
        "sku": "MONITOR-001",
        "description": "Professional 4K display",
        "supplier_id": 1,
        "unit_price": "499.99",
        "stock_quantity": 35,
        "reorder_level": 10,
        "created_at": "2026-02-04T17:24:02.047Z",
        "updated_at": "2026-02-04T17:24:02.047Z",
        "user_id": 8,
        "primary_state": "available",
        "last_movement_date": "2026-02-04T17:24:02.047Z",
        "supplier_name": "TechParts Inc",
        "total_value": "17499.65",
        "stock_status": "OVERSTOCK"
      },
      {
        "id": 20,
        "name": "saiodaod",
        "sku": "oniajsodi",
        "description": "ioasdioadio",
        "supplier_id": null,
        "unit_price": "123.00",
        "stock_quantity": 123,
        "reorder_level": 1230,
        "created_at": "2026-02-11T14:52:20.859Z",
        "updated_at": "2026-02-11T14:52:20.859Z",
        "user_id": 1,
        "primary_state": "available",
        "last_movement_date": "2026-02-11T14:52:20.859Z",
        "supplier_name": null,
        "total_value": "15129.00",
        "stock_status": "LOW_STOCK"
      },
      {
        "id": 7,
        "name": "Tablet 10\" Pro",
        "sku": "TABLET-001",
        "description": "Professional tablet with stylus",
        "supplier_id": 5,
        "unit_price": "649.99",
        "stock_quantity": 18,
        "reorder_level": 8,
        "created_at": "2026-02-04T17:24:02.047Z",
        "updated_at": "2026-02-04T17:24:02.047Z",
        "user_id": 8,
        "primary_state": "available",
        "last_movement_date": "2026-02-04T17:24:02.047Z",
        "supplier_name": "Hardware Express",
        "total_value": "11699.82",
        "stock_status": "NORMAL"
      },
      {
        "id": 19,
        "name": "aosijdaoisod",
        "sku": "oisdoai",
        "description": "",
        "supplier_id": null,
        "unit_price": "1000.00",
        "stock_quantity": 10,
        "reorder_level": 10,
        "created_at": "2026-02-07T10:08:40.570Z",
        "updated_at": "2026-02-11T16:59:23.579Z",
        "user_id": 10,
        "primary_state": "available",
        "last_movement_date": "2026-02-07T10:08:40.570Z",
        "supplier_name": null,
        "total_value": "10000.00",
        "stock_status": "LOW_STOCK"
      },
      {
        "id": 6,
        "name": "Wireless Headphones",
        "sku": "HEADPHONES-001",
        "description": "Noise-cancelling wireless headphones",
        "supplier_id": 4,
        "unit_price": "199.99",
        "stock_quantity": 45,
        "reorder_level": 12,
        "created_at": "2026-02-04T17:24:02.047Z",
        "updated_at": "2026-02-04T17:24:02.047Z",
        "user_id": 8,
        "primary_state": "available",
        "last_movement_date": "2026-02-04T17:24:02.047Z",
        "supplier_name": "Digital Solutions Ltd",
        "total_value": "8999.55",
        "stock_status": "OVERSTOCK"
      },
      {
        "id": 5,
        "name": "USB-C Cable 2m",
        "sku": "CABLE-USB-001",
        "description": "High-speed USB-C cable",
        "supplier_id": 3,
        "unit_price": "19.99",
        "stock_quantity": 400,
        "reorder_level": 100,
        "created_at": "2026-02-04T17:24:02.047Z",
        "updated_at": "2026-02-04T17:24:02.047Z",
        "user_id": 8,
        "primary_state": "available",
        "last_movement_date": "2026-02-04T17:24:02.047Z",
        "supplier_name": "Component Masters",
        "total_value": "7996.00",
        "stock_status": "OVERSTOCK"
      },
      {
        "id": 9,
        "name": "External SSD 1TB",
        "sku": "SSD-001",
        "description": "Portable external SSD drive",
        "supplier_id": 7,
        "unit_price": "129.99",
        "stock_quantity": 55,
        "reorder_level": 15,
        "created_at": "2026-02-04T17:24:02.047Z",
        "updated_at": "2026-02-04T17:24:02.047Z",
        "user_id": 8,
        "primary_state": "available",
        "last_movement_date": "2026-02-04T17:24:02.047Z",
        "supplier_name": "Innovative Components",
        "total_value": "7149.45",
        "stock_status": "OVERSTOCK"
      },
      {
        "id": 8,
        "name": "Webcam HD Pro",
        "sku": "WEBCAM-001",
        "description": "1080p HD webcam with auto-focus",
        "supplier_id": 6,
        "unit_price": "79.99",
        "stock_quantity": 85,
        "reorder_level": 20,
        "created_at": "2026-02-04T17:24:02.047Z",
        "updated_at": "2026-02-04T17:24:02.047Z",
        "user_id": 8,
        "primary_state": "available",
        "last_movement_date": "2026-02-04T17:24:02.047Z",
        "supplier_name": "Premium Tech Supply",
        "total_value": "6799.15",
        "stock_status": "OVERSTOCK"
      },
      {
        "id": 14,
        "name": "Security Camera",
        "sku": "CAMERA-001",
        "description": "IP security camera with night vision",
        "supplier_id": 12,
        "unit_price": "149.99",
        "stock_quantity": 42,
        "reorder_level": 12,
        "created_at": "2026-02-04T17:24:02.047Z",
        "updated_at": "2026-02-04T17:24:02.047Z",
        "user_id": 8,
        "primary_state": "available",
        "last_movement_date": "2026-02-04T17:24:02.047Z",
        "supplier_name": "Professional Equipment Co",
        "total_value": "6299.58",
        "stock_status": "OVERSTOCK"
      },
      {
        "id": 3,
        "name": "Mechanical Keyboard",
        "sku": "KEYBOARD-001",
        "description": "RGB mechanical keyboard",
        "supplier_id": 2,
        "unit_price": "89.99",
        "stock_quantity": 60,
        "reorder_level": 15,
        "created_at": "2026-02-04T17:24:02.047Z",
        "updated_at": "2026-02-04T17:24:02.047Z",
        "user_id": 8,
        "primary_state": "available",
        "last_movement_date": "2026-02-04T17:24:02.047Z",
        "supplier_name": "Global Electronics",
        "total_value": "5399.40",
        "stock_status": "OVERSTOCK"
      },
      {
        "id": 10,
        "name": "Docking Station",
        "sku": "DOCK-001",
        "description": "Universal USB-C docking station",
        "supplier_id": 8,
        "unit_price": "159.99",
        "stock_quantity": 32,
        "reorder_level": 10,
        "created_at": "2026-02-04T17:24:02.047Z",
        "updated_at": "2026-02-04T17:24:02.047Z",
        "user_id": 8,
        "primary_state": "available",
        "last_movement_date": "2026-02-04T17:24:02.047Z",
        "supplier_name": "Reliable Electronics Co",
        "total_value": "5119.68",
        "stock_status": "OVERSTOCK"
      },
      {
        "id": 12,
        "name": "Bluetooth Speaker",
        "sku": "SPEAKER-001",
        "description": "Portable Bluetooth speaker",
        "supplier_id": 10,
        "unit_price": "69.99",
        "stock_quantity": 72,
        "reorder_level": 18,
        "created_at": "2026-02-04T17:24:02.047Z",
        "updated_at": "2026-02-04T17:24:02.047Z",
        "user_id": 8,
        "primary_state": "available",
        "last_movement_date": "2026-02-04T17:24:02.047Z",
        "supplier_name": "Quality Parts Direct",
        "total_value": "5039.28",
        "stock_status": "OVERSTOCK"
      },
      {
        "id": 11,
        "name": "Wireless Charger",
        "sku": "CHARGER-001",
        "description": "Fast wireless charging pad",
        "supplier_id": 9,
        "unit_price": "39.99",
        "stock_quantity": 95,
        "reorder_level": 25,
        "created_at": "2026-02-04T17:24:02.047Z",
        "updated_at": "2026-02-04T17:24:02.047Z",
        "user_id": 8,
        "primary_state": "available",
        "last_movement_date": "2026-02-04T17:24:02.047Z",
        "supplier_name": "Advanced Systems Inc",
        "total_value": "3799.05",
        "stock_status": "OVERSTOCK"
      },
      {
        "id": 2,
        "name": "Wireless Mouse",
        "sku": "MOUSE-001",
        "description": "Ergonomic wireless mouse",
        "supplier_id": 2,
        "unit_price": "29.99",
        "stock_quantity": 115,
        "reorder_level": 30,
        "created_at": "2026-02-04T17:24:02.047Z",
        "updated_at": "2026-02-07T13:36:21.170Z",
        "user_id": 8,
        "primary_state": "available",
        "last_movement_date": "2026-02-04T17:24:02.047Z",
        "supplier_name": "Global Electronics",
        "total_value": "3448.85",
        "stock_status": "OVERSTOCK"
      },
      {
        "id": 21,
        "name": "jasndkj",
        "sku": "janskjdnasd",
        "description": "askjdnkajd",
        "supplier_id": null,
        "unit_price": "23.00",
        "stock_quantity": 123,
        "reorder_level": 123,
        "created_at": "2026-02-11T16:58:41.441Z",
        "updated_at": "2026-02-11T16:58:41.441Z",
        "user_id": 1,
        "primary_state": "available",
        "last_movement_date": "2026-02-11T16:58:41.441Z",
        "supplier_name": null,
        "total_value": "2829.00",
        "stock_status": "LOW_STOCK"
      },
      {
        "id": 13,
        "name": "Network Switch 8-Port",
        "sku": "SWITCH-001",
        "description": "Gigabit Ethernet switch",
        "supplier_id": 11,
        "unit_price": "89.99",
        "stock_quantity": 28,
        "reorder_level": 8,
        "created_at": "2026-02-04T17:24:02.047Z",
        "updated_at": "2026-02-04T17:24:02.047Z",
        "user_id": 8,
        "primary_state": "available",
        "last_movement_date": "2026-02-04T17:24:02.047Z",
        "supplier_name": "Smart Tech Distributors",
        "total_value": "2519.72",
        "stock_status": "OVERSTOCK"
      },
      {
        "id": 16,
        "name": "Smart Watch",
        "sku": "WATCH-001",
        "description": "Fitness tracking smart watch",
        "supplier_id": 9,
        "unit_price": "249.99",
        "stock_quantity": 2,
        "reorder_level": 10,
        "created_at": "2026-02-04T17:24:02.047Z",
        "updated_at": "2026-02-04T17:24:02.047Z",
        "user_id": 8,
        "primary_state": "available",
        "last_movement_date": "2026-02-04T17:24:02.047Z",
        "supplier_name": "Advanced Systems Inc",
        "total_value": "499.98",
        "stock_status": "LOW_STOCK"
      },
      {
        "id": 15,
        "name": "Power Bank 20000mAh",
        "sku": "POWERBANK-001",
        "description": "High-capacity portable power bank",
        "supplier_id": 5,
        "unit_price": "49.99",
        "stock_quantity": 3,
        "reorder_level": 15,
        "created_at": "2026-02-04T17:24:02.047Z",
        "updated_at": "2026-02-04T17:24:02.047Z",
        "user_id": 8,
        "primary_state": "available",
        "last_movement_date": "2026-02-04T17:24:02.047Z",
        "supplier_name": "Hardware Express",
        "total_value": "149.97",
        "stock_status": "LOW_STOCK"
      },
      {
        "id": 1,
        "name": "Business Laptop Pro",
        "sku": "LAPTOP-001",
        "description": "High-performance laptop",
        "supplier_id": 1,
        "unit_price": "1299.99",
        "stock_quantity": -42,
        "reorder_level": 5,
        "created_at": "2026-02-04T17:24:02.047Z",
        "updated_at": "2026-02-11T17:18:56.184Z",
        "user_id": 8,
        "primary_state": "available",
        "last_movement_date": "2026-02-04T17:24:02.047Z",
        "supplier_name": "TechParts Inc",
        "total_value": "-54599.58",
        "stock_status": "LOW_STOCK"
      }
    ],
    "inventorySummary": [
      {
        "total_products": "19",
        "total_inventory_value": "65777.55",
        "average_price": "260.8336842105263158",
        "total_units": "1301",
        "out_of_stock_count": "0",
        "low_stock_count": "6",
        "overstock_count": "12"
      }
    ],
    "ordersInPeriod": [
      {
        "id": 32,
        "order_number": "ORD-1770485792792-738",
        "customer_name": " d sniosdoi",
        "status": "COMPLETED",
        "created_at": "2026-02-07T17:36:32.790Z",
        "updated_at": "2026-02-08T11:56:56.244Z",
        "user_id": 10,
        "item_count": "1",
        "total_amount": "10000.00",
        "order_date": "2026-02-06T18:30:00.000Z"
      },
      {
        "id": 18,
        "order_number": "ORD-1770231034805-937",
        "customer_name": "Test User Order",
        "status": "COMPLETED",
        "created_at": "2026-02-04T18:50:34.793Z",
        "updated_at": "2026-02-08T07:46:43.030Z",
        "user_id": 8,
        "item_count": "1",
        "total_amount": "100.00",
        "order_date": "2026-02-04T18:30:00.000Z"
      },
      {
        "id": 17,
        "order_number": "ORD-1770229726426-634",
        "customer_name": "Frontend Test Customer",
        "status": "COMPLETED",
        "created_at": "2026-02-04T18:28:46.420Z",
        "updated_at": "2026-02-07T13:36:21.170Z",
        "user_id": 8,
        "item_count": "2",
        "total_amount": "1359.97",
        "order_date": "2026-02-03T18:30:00.000Z"
      },
      {
        "id": 16,
        "order_number": "ORD-1770229681903-782",
        "customer_name": "dfdsfsd",
        "status": "COMPLETED",
        "created_at": "2026-02-04T18:28:01.897Z",
        "updated_at": "2026-02-07T13:46:27.461Z",
        "user_id": 8,
        "item_count": "1",
        "total_amount": "1299.99",
        "order_date": "2026-02-03T18:30:00.000Z"
      },
      {
        "id": 15,
        "order_number": "ORD-1770229657245-14",
        "customer_name": "Test Customer Working",
        "status": "COMPLETED",
        "created_at": "2026-02-04T18:27:37.240Z",
        "updated_at": "2026-02-07T17:26:03.985Z",
        "user_id": 8,
        "item_count": "1",
        "total_amount": "2599.98",
        "order_date": "2026-02-03T18:30:00.000Z"
      },
      {
        "id": 7,
        "order_number": "ORD-1770228838901-765",
        "customer_name": "Test Customer",
        "status": "COMPLETED",
        "created_at": "2026-02-04T18:13:58.893Z",
        "updated_at": "2026-02-07T17:31:45.037Z",
        "user_id": 8,
        "item_count": "1",
        "total_amount": "2599.98",
        "order_date": "2026-02-03T18:30:00.000Z"
      },
      {
        "id": 2,
        "order_number": "PO-2025-002",
        "customer_name": "Globex",
        "status": "COMPLETED",
        "created_at": "2026-02-04T17:24:02.047Z",
        "updated_at": "2026-02-04T17:24:02.047Z",
        "user_id": 8,
        "item_count": "2",
        "total_amount": "4498.74",
        "order_date": "2026-02-03T18:30:00.000Z"
      }
    ],
    "topSellingProducts": [
      {
        "name": "USB-C Cable 2m",
        "sku": "CABLE-USB-001",
        "total_sold": "120",
        "total_revenue": "1798.80",
        "order_count": "1"
      },
      {
        "name": "aosijdaoisod",
        "sku": "oisdoai",
        "total_sold": "10",
        "total_revenue": "10000.00",
        "order_count": "1"
      },
      {
        "name": "Business Laptop Pro",
        "sku": "LAPTOP-001",
        "total_sold": "7",
        "total_revenue": "7899.94",
        "order_count": "5"
      },
      {
        "name": "27\" 4K Monitor",
        "sku": "MONITOR-001",
        "total_sold": "6",
        "total_revenue": "2699.94",
        "order_count": "1"
      },
      {
        "name": "Wireless Mouse",
        "sku": "MOUSE-001",
        "total_sold": "2",
        "total_revenue": "59.98",
        "order_count": "1"
      }
    ],
    "supplierPerformance": [
      {
        "name": "Hardware Express",
        "contact_email": "support@hardwareexpress.com",
        "product_count": "2",
        "total_value": "11849.79",
        "low_stock_products": "1",
        "avg_product_price": "349.9900000000000000"
      },
      {
        "name": "Digital Solutions Ltd",
        "contact_email": "orders@digitalsolutions.com",
        "product_count": "1",
        "total_value": "8999.55",
        "low_stock_products": "0",
        "avg_product_price": "199.9900000000000000"
      },
      {
        "name": "Global Electronics",
        "contact_email": "hello@globalelec.com",
        "product_count": "2",
        "total_value": "8848.25",
        "low_stock_products": "0",
        "avg_product_price": "59.9900000000000000"
      },
      {
        "name": "Component Masters",
        "contact_email": "sales@compmasters.com",
        "product_count": "1",
        "total_value": "7996.00",
        "low_stock_products": "0",
        "avg_product_price": "19.9900000000000000"
      },
      {
        "name": "Innovative Components",
        "contact_email": "info@innovativecomp.com",
        "product_count": "1",
        "total_value": "7149.45",
        "low_stock_products": "0",
        "avg_product_price": "129.9900000000000000"
      },
      {
        "name": "Premium Tech Supply",
        "contact_email": "sales@premiumtech.com",
        "product_count": "1",
        "total_value": "6799.15",
        "low_stock_products": "0",
        "avg_product_price": "79.9900000000000000"
      },
      {
        "name": "Professional Equipment Co",
        "contact_email": "business@proequipment.com",
        "product_count": "1",
        "total_value": "6299.58",
        "low_stock_products": "0",
        "avg_product_price": "149.9900000000000000"
      },
      {
        "name": "Reliable Electronics Co",
        "contact_email": "contact@reliableelec.com",
        "product_count": "1",
        "total_value": "5119.68",
        "low_stock_products": "0",
        "avg_product_price": "159.9900000000000000"
      },
      {
        "name": "Quality Parts Direct",
        "contact_email": "orders@qualityparts.com",
        "product_count": "1",
        "total_value": "5039.28",
        "low_stock_products": "0",
        "avg_product_price": "69.9900000000000000"
      },
      {
        "name": "Advanced Systems Inc",
        "contact_email": "procurement@advancedsys.com",
        "product_count": "2",
        "total_value": "4299.03",
        "low_stock_products": "1",
        "avg_product_price": "144.9900000000000000"
      },
      {
        "name": "Smart Tech Distributors",
        "contact_email": "sales@smarttechdist.com",
        "product_count": "1",
        "total_value": "2519.72",
        "low_stock_products": "0",
        "avg_product_price": "89.9900000000000000"
      },
      {
        "name": "newsupp",
        "contact_email": "newsupp@gmail.com",
        "product_count": "0",
        "total_value": null,
        "low_stock_products": "0",
        "avg_product_price": null
      },
      {
        "name": "newsupp123",
        "contact_email": "aijsdoiajd@gmail.com",
        "product_count": "0",
        "total_value": null,
        "low_stock_products": "0",
        "avg_product_price": null
      },
      {
        "name": "newsuppppppppppp",
        "contact_email": "newsup@gmail.com",
        "product_count": "0",
        "total_value": null,
        "low_stock_products": "0",
        "avg_product_price": null
      },
      {
        "name": "TechParts Inc",
        "contact_email": "contact@techparts.com",
        "product_count": "2",
        "total_value": "-37099.93",
        "low_stock_products": "1",
        "avg_product_price": "899.9900000000000000"
      }
    ],
    "stockAlerts": [
      {
        "name": "saiodaod",
        "sku": "oniajsodi",
        "stock_quantity": 123,
        "reorder_level": 1230,
        "supplier_name": null,
        "contact_email": null,
        "units_needed": 1107,
        "reorder_cost": "136161.00"
      },
      {
        "name": "Business Laptop Pro",
        "sku": "LAPTOP-001",
        "stock_quantity": -42,
        "reorder_level": 5,
        "supplier_name": "TechParts Inc",
        "contact_email": "contact@techparts.com",
        "units_needed": 47,
        "reorder_cost": "61099.53"
      },
      {
        "name": "Power Bank 20000mAh",
        "sku": "POWERBANK-001",
        "stock_quantity": 3,
        "reorder_level": 15,
        "supplier_name": "Hardware Express",
        "contact_email": "support@hardwareexpress.com",
        "units_needed": 12,
        "reorder_cost": "599.88"
      },
      {
        "name": "Smart Watch",
        "sku": "WATCH-001",
        "stock_quantity": 2,
        "reorder_level": 10,
        "supplier_name": "Advanced Systems Inc",
        "contact_email": "procurement@advancedsys.com",
        "units_needed": 8,
        "reorder_cost": "1999.92"
      },
      {
        "name": "aosijdaoisod",
        "sku": "oisdoai",
        "stock_quantity": 10,
        "reorder_level": 10,
        "supplier_name": null,
        "contact_email": null,
        "units_needed": 0,
        "reorder_cost": "0.00"
      },
      {
        "name": "jasndkj",
        "sku": "janskjdnasd",
        "stock_quantity": 123,
        "reorder_level": 123,
        "supplier_name": null,
        "contact_email": null,
        "units_needed": 0,
        "reorder_cost": "0.00"
      }
    ]
  },
  "analysis": {
    "summary": {
      "totalProducts": 19,
      "totalValue": 65777.55,
      "totalUnits": 1301,
      "avgPrice": 50.56
    },
    "stockStatus": {
      "normal": 1,
      "lowStock": 6,
      "outOfStock": 0,
      "overstock": 12,
      "normalPercent": 5,
      "lowStockPercent": 32,
      "outOfStockPercent": 0,
      "overstockPercent": 63
    },
    "topProducts": [
      {
        "id": 4,
        "name": "27\" 4K Monitor",
        "sku": "MONITOR-001",
        "description": "Professional 4K display",
        "supplier_id": 1,
        "unit_price": "499.99",
        "stock_quantity": 35,
        "reorder_level": 10,
        "created_at": "2026-02-04T17:24:02.047Z",
        "updated_at": "2026-02-04T17:24:02.047Z",
        "user_id": 8,
        "primary_state": "available",
        "last_movement_date": "2026-02-04T17:24:02.047Z",
        "supplier_name": "TechParts Inc",
        "total_value": "17499.65",
        "stock_status": "OVERSTOCK"
      },
      {
        "id": 20,
        "name": "saiodaod",
        "sku": "oniajsodi",
        "description": "ioasdioadio",
        "supplier_id": null,
        "unit_price": "123.00",
        "stock_quantity": 123,
        "reorder_level": 1230,
        "created_at": "2026-02-11T14:52:20.859Z",
        "updated_at": "2026-02-11T14:52:20.859Z",
        "user_id": 1,
        "primary_state": "available",
        "last_movement_date": "2026-02-11T14:52:20.859Z",
        "supplier_name": null,
        "total_value": "15129.00",
        "stock_status": "LOW_STOCK"
      },
      {
        "id": 7,
        "name": "Tablet 10\" Pro",
        "sku": "TABLET-001",
        "description": "Professional tablet with stylus",
        "supplier_id": 5,
        "unit_price": "649.99",
        "stock_quantity": 18,
        "reorder_level": 8,
        "created_at": "2026-02-04T17:24:02.047Z",
        "updated_at": "2026-02-04T17:24:02.047Z",
        "user_id": 8,
        "primary_state": "available",
        "last_movement_date": "2026-02-04T17:24:02.047Z",
        "supplier_name": "Hardware Express",
        "total_value": "11699.82",
        "stock_status": "NORMAL"
      },
      {
        "id": 19,
        "name": "aosijdaoisod",
        "sku": "oisdoai",
        "description": "",
        "supplier_id": null,
        "unit_price": "1000.00",
        "stock_quantity": 10,
        "reorder_level": 10,
        "created_at": "2026-02-07T10:08:40.570Z",
        "updated_at": "2026-02-11T16:59:23.579Z",
        "user_id": 10,
        "primary_state": "available",
        "last_movement_date": "2026-02-07T10:08:40.570Z",
        "supplier_name": null,
        "total_value": "10000.00",
        "stock_status": "LOW_STOCK"
      },
      {
        "id": 6,
        "name": "Wireless Headphones",
        "sku": "HEADPHONES-001",
        "description": "Noise-cancelling wireless headphones",
        "supplier_id": 4,
        "unit_price": "199.99",
        "stock_quantity": 45,
        "reorder_level": 12,
        "created_at": "2026-02-04T17:24:02.047Z",
        "updated_at": "2026-02-04T17:24:02.047Z",
        "user_id": 8,
        "primary_state": "available",
        "last_movement_date": "2026-02-04T17:24:02.047Z",
        "supplier_name": "Digital Solutions Ltd",
        "total_value": "8999.55",
        "stock_status": "OVERSTOCK"
      }
    ],
    "criticalAlerts": [
      {
        "name": "saiodaod",
        "sku": "oniajsodi",
        "stock_quantity": 123,
        "reorder_level": 1230,
        "supplier_name": null,
        "contact_email": null,
        "units_needed": 1107,
        "reorder_cost": "136161.00"
      },
      {
        "name": "Business Laptop Pro",
        "sku": "LAPTOP-001",
        "stock_quantity": -42,
        "reorder_level": 5,
        "supplier_name": "TechParts Inc",
        "contact_email": "contact@techparts.com",
        "units_needed": 47,
        "reorder_cost": "61099.53"
      },
      {
        "name": "Power Bank 20000mAh",
        "sku": "POWERBANK-001",
        "stock_quantity": 3,
        "reorder_level": 15,
        "supplier_name": "Hardware Express",
        "contact_email": "support@hardwareexpress.com",
        "units_needed": 12,
        "reorder_cost": "599.88"
      },
      {
        "name": "Smart Watch",
        "sku": "WATCH-001",
        "stock_quantity": 2,
        "reorder_level": 10,
        "supplier_name": "Advanced Systems Inc",
        "contact_email": "procurement@advancedsys.com",
        "units_needed": 8,
        "reorder_cost": "1999.92"
      },
      {
        "name": "aosijdaoisod",
        "sku": "oisdoai",
        "stock_quantity": 10,
        "reorder_level": 10,
        "supplier_name": null,
        "contact_email": null,
        "units_needed": 0,
        "reorder_cost": "0.00"
      }
    ],
    "topSuppliers": [
      {
        "name": "Hardware Express",
        "contact_email": "support@hardwareexpress.com",
        "product_count": "2",
        "total_value": "11849.79",
        "low_stock_products": "1",
        "avg_product_price": "349.9900000000000000"
      },
      {
        "name": "Digital Solutions Ltd",
        "contact_email": "orders@digitalsolutions.com",
        "product_count": "1",
        "total_value": "8999.55",
        "low_stock_products": "0",
        "avg_product_price": "199.9900000000000000"
      },
      {
        "name": "Global Electronics",
        "contact_email": "hello@globalelec.com",
        "product_count": "2",
        "total_value": "8848.25",
        "low_stock_products": "0",
        "avg_product_price": "59.9900000000000000"
      },
      {
        "name": "Component Masters",
        "contact_email": "sales@compmasters.com",
        "product_count": "1",
        "total_value": "7996.00",
        "low_stock_products": "0",
        "avg_product_price": "19.9900000000000000"
      },
      {
        "name": "Innovative Components",
        "contact_email": "info@innovativecomp.com",
        "product_count": "1",
        "total_value": "7149.45",
        "low_stock_products": "0",
        "avg_product_price": "129.9900000000000000"
      }
    ],
    "periodActivity": {
      "totalOrders": 7,
      "totalOrderValue": 22458.659999999996,
      "topSelling": "USB-C Cable 2m"
    },
    "financial": {
      "turnoverRisk": "High",
      "capitalTiedUp": 80069.36000000002,
      "reorderInvestment": 199860.33000000002
    }
  }
}